kisa.py
kisaBobPkgs.py
test_bob8gook.py
testbob8gook.py
whois.py
kisaBobPkgs-1.0.0.21.dist-info/METADATA
kisaBobPkgs-1.0.0.21.dist-info/WHEEL
kisaBobPkgs-1.0.0.21.dist-info/top_level.txt
kisaBobPkgs-1.0.0.21.dist-info/RECORD
