Metadata-Version: 2.1
Name: kisaBobPkgs
Version: 1.0.0.21
Summary: bob8gook
Home-page: https://github.com/woounnan
Author: bob8gook
Author-email: hyeok.jang@lotte.net
License: MIT
Requires-Python: >=3
